file_captain/__init__.py
file_captain/core.py
file_captain/py.typed
file_captain-1.0.3.dist-info/METADATA
file_captain-1.0.3.dist-info/WHEEL
file_captain-1.0.3.dist-info/licenses/LICENSE
file_captain-1.0.3.dist-info/RECORD
