Metadata-Version: 2.4
Name: file-captain
Version: 1.0.3
Summary: Utility function to read and write files
Project-URL: Homepage, https://github.com/philipgautschi/file-captain
Project-URL: Repository, https://github.com/philipgautschi/file-captain
Project-URL: Issues, https://github.com/philipgautschi/file-captain/issues
Author-email: Philip Gautschi <philips.python.projects@gmail.com>, Nicolas Brehm <philips.python.projects+friends@gmail.com>
Maintainer-email: Philip Gautschi <philips.python.projects@gmail.com>
License: MIT
License-File: LICENSE
Keywords: file,io,json,pickle,text,toml,utilities,yaml
Classifier: Development Status :: 5 - Production/Stable
Classifier: Intended Audience :: Developers
Classifier: License :: OSI Approved :: MIT License
Classifier: Operating System :: OS Independent
Classifier: Programming Language :: Python :: 3
Classifier: Programming Language :: Python :: 3.11
Classifier: Programming Language :: Python :: 3.12
Classifier: Programming Language :: Python :: 3.13
Classifier: Topic :: Software Development :: Libraries :: Python Modules
Classifier: Topic :: System :: Filesystems
Classifier: Topic :: Utilities
Classifier: Typing :: Typed
Requires-Python: >=3.11
Requires-Dist: pyyaml>=6.0
Requires-Dist: tomli-w>=1.0.0
Provides-Extra: dev
Requires-Dist: black; extra == 'dev'
Requires-Dist: isort; extra == 'dev'
Requires-Dist: mypy; extra == 'dev'
Requires-Dist: pytest; extra == 'dev'
Requires-Dist: pytest-cov; extra == 'dev'
Requires-Dist: types-pyyaml; extra == 'dev'
